asu_ods_integration/__init__.py
asu_ods_integration/admin.py
asu_ods_integration/apps.py
asu_ods_integration/constants.py
asu_ods_integration/exceptions.py
asu_ods_integration/forms.py
asu_ods_integration/import_containers.py
asu_ods_integration/import_contracts.py
asu_ods_integration/models.py
asu_ods_integration/tasks.py
asu_ods_integration/tests.py
asu_ods_integration/urls.py
asu_ods_integration/utilites.py
asu_ods_integration/views.py
asu_ods_integration/черновик.json
asu_ods_integration/черновик.py
asu_ods_integration/documentation/import_containers.txt
asu_ods_integration/external/__init__.py
asu_ods_integration/external/asu_ods.py
asu_ods_integration/external/csv_import.py
asu_ods_integration/management/__init__.py
asu_ods_integration/management/commands/__init__.py
asu_ods_integration/management/commands/asu_ods_delete_all_import.py
asu_ods_integration/management/commands/asu_ods_find_handmade_mno.py
asu_ods_integration/management/commands/asu_ods_import_containers.py
asu_ods_integration/management/commands/asu_ods_import_contracts.py
asu_ods_integration/management/commands/find_nearest_mno_for_raw_data.py
asu_ods_integration/management/commands/save_raw_data_on_waste_site.py
asu_ods_integration/migrations/0001_squashed_0007_complete_field_external_source.py
asu_ods_integration/migrations/0002_asuodstransport.py
asu_ods_integration/migrations/0003_remove_asuodstransport_owner_and_more.py
asu_ods_integration/migrations/0004_auto_20231212_0830.py
asu_ods_integration/migrations/0005_migrate_wastesite_comment.py
asu_ods_integration/migrations/0006_wastesiterawdata.py
asu_ods_integration/migrations/0007_wastesiterawdata_nearest_mno.py
asu_ods_integration/migrations/__init__.py
asu_ods_integration/templates/delete_containers.html
asu_ods_integration/templates/import_containers.html
asu_ods_integration/templates/import_contracts.html
asu_ods_integration/templates/import_raw_data.html
asu_ods_integration/templates/menu_of_commands.html
big3_integration_asu_ods-1.5.dist-info/METADATA
big3_integration_asu_ods-1.5.dist-info/WHEEL
big3_integration_asu_ods-1.5.dist-info/licenses/LICENSE
big3_integration_asu_ods-1.5.dist-info/RECORD
